bbdd_utils/__init__.py
bbdd_utils/functions.py
bbdd_utils/utils.py
bbdd_utils-0.3.16.dist-info/licenses/LICENSE
bbdd_utils-0.3.16.dist-info/METADATA
bbdd_utils-0.3.16.dist-info/WHEEL
bbdd_utils-0.3.16.dist-info/top_level.txt
bbdd_utils-0.3.16.dist-info/RECORD
