Metadata-Version: 2.4
Name: bbdd_utils
Version: 0.3.16
Summary: insertar datos en una base de datos SQL o NoSQL
Author: Luis_J_Domingo
License-File: LICENSE
Dynamic: author
Dynamic: description
Dynamic: description-content-type
Dynamic: license-file
Dynamic: summary
